topsis_nishchay_102217036/__init__.py
topsis_nishchay_102217036/main.py
topsis_nishchay_102217036-1.0.0.dist-info/LICENCE
topsis_nishchay_102217036-1.0.0.dist-info/METADATA
topsis_nishchay_102217036-1.0.0.dist-info/WHEEL
topsis_nishchay_102217036-1.0.0.dist-info/entry_points.txt
topsis_nishchay_102217036-1.0.0.dist-info/top_level.txt
topsis_nishchay_102217036-1.0.0.dist-info/RECORD
